subprocess_mem_only/LICENSE
subprocess_mem_only/README.MD
subprocess_mem_only/__init__.py
subprocess_mem_only/requirements.txt
subprocess_mem_only/thirdparty.json
subprocess_mem_only-0.10.dist-info/LICENSE.rst
subprocess_mem_only-0.10.dist-info/METADATA
subprocess_mem_only-0.10.dist-info/WHEEL
subprocess_mem_only-0.10.dist-info/top_level.txt
subprocess_mem_only-0.10.dist-info/RECORD
